pathaia/__init__.py
pathaia/datasets/__init__.py
pathaia/datasets/data.py
pathaia/datasets/errors.py
pathaia/datasets/functional_api.py
pathaia/datasets/object_api.py
pathaia/graphs/__init__.py
pathaia/graphs/clustering.py
pathaia/graphs/errors.py
pathaia/graphs/functional_api.py
pathaia/graphs/kruskal.py
pathaia/graphs/object_api.py
pathaia/graphs/types.py
pathaia/patches/__init__.py
pathaia/patches/compat.py
pathaia/patches/errors.py
pathaia/patches/filters.py
pathaia/patches/functional_api.py
pathaia/patches/object_api.py
pathaia/patches/slide_filters.py
pathaia/patches/visu.py
pathaia/semantic/__init__.py
pathaia/semantic/functional_api.py
pathaia/util/__init__.py
pathaia/util/basic.py
pathaia/util/convert.py
pathaia/util/images.py
pathaia/util/management.py
pathaia/util/paths.py
pathaia/util/types.py
pathaia-0.2.6.dist-info/licenses/LICENSE
tests/__init__.py
tests/data.py
tests/helpers.py
pathaia-0.2.6.dist-info/METADATA
pathaia-0.2.6.dist-info/WHEEL
pathaia-0.2.6.dist-info/top_level.txt
pathaia-0.2.6.dist-info/RECORD
