Metadata-Version: 2.4
Name: pathaia
Version: 0.2.6
Summary: procedures for wsi analysis
Author: Arnaud Abreu
Author-email: arnaud.abreu.p@gmail.com
License-File: LICENSE
Requires-Dist: fastcore<2,>=1
Requires-Dist: numpy<2,>=1
Requires-Dist: tqdm>=4
Requires-Dist: openslide-python>=1.1
Requires-Dist: opencv-python-headless>=4
Requires-Dist: scikit-image<1,>=0.19
Requires-Dist: matplotlib>=3
Requires-Dist: nptyping<3,>=2
Requires-Dist: pandas>=1
Requires-Dist: dataclasses
Requires-Dist: sortedcontainers<3,>=2
Requires-Dist: ordered-set<5,>=4
Requires-Dist: shapely>=1
Requires-Dist: scikit-learn<2,>=1
Dynamic: author
Dynamic: author-email
Dynamic: description
Dynamic: description-content-type
Dynamic: license-file
Dynamic: requires-dist
Dynamic: summary
